<?xml version = "1.0" encoding = "UTF-8" ?>
<Computer id="armyDatanet" 
name="NORAD DATANET" 
security="0"  
type="3">

 <!-- Accounts -->
<adminPass pass="defcon1" />

<admin type="progress" />

  <portsForCrack val="1" />
  <ports>21</ports>
  <proxy time="1" />
  <firewall level="6" solution="defcon" additionalTime="0.5"/>
  <trace time="500" />

  <file path="home" name="MISSILE_LUNCH_SILOS.txt">
ALPHA: 68.56.23.07
BRAVO: 40.60.21.31
CHARLIE: 31.63.19.87
  </file>

  <encryptedFile path="home" name="MISSILE_LUNCH_CODE.dec" extension=".txt" ip="armyDatanet" header="NORAD DATANET" pass="CPE1704TKS">
00000000
  </encryptedFile>

<dlink target="armyWOPR" />
  
</Computer>